odoo/addons/product_multi_barcode_supplierinfo/README.rst
odoo/addons/product_multi_barcode_supplierinfo/__init__.py
odoo/addons/product_multi_barcode_supplierinfo/__manifest__.py
odoo/addons/product_multi_barcode_supplierinfo/hook.py
odoo/addons/product_multi_barcode_supplierinfo/i18n/product_multi_barcode_supplierinfo.pot
odoo/addons/product_multi_barcode_supplierinfo/models/__init__.py
odoo/addons/product_multi_barcode_supplierinfo/models/product_barcode.py
odoo/addons/product_multi_barcode_supplierinfo/models/supplierinfo.py
odoo/addons/product_multi_barcode_supplierinfo/readme/CONTRIBUTORS.rst
odoo/addons/product_multi_barcode_supplierinfo/readme/DESCRIPTION.rst
odoo/addons/product_multi_barcode_supplierinfo/static/description/icon.png
odoo/addons/product_multi_barcode_supplierinfo/static/description/index.html
odoo/addons/product_multi_barcode_supplierinfo/tests/__init__.py
odoo/addons/product_multi_barcode_supplierinfo/tests/test_product_multi_barcode_supplierinfo.py
odoo/addons/product_multi_barcode_supplierinfo/views/product_template_view.xml
odoo14_addon_product_multi_barcode_supplierinfo-14.0.1.0.1.dist-info/METADATA
odoo14_addon_product_multi_barcode_supplierinfo-14.0.1.0.1.dist-info/WHEEL
odoo14_addon_product_multi_barcode_supplierinfo-14.0.1.0.1.dist-info/top_level.txt
odoo14_addon_product_multi_barcode_supplierinfo-14.0.1.0.1.dist-info/RECORD
