Metadata-Version: 2.1
Name: odoo14-addon-product-multi-barcode-supplierinfo
Version: 14.0.1.0.1
Summary: Adds supplier pricelist barcode in product barcode
Home-page: https://github.com/OCA/stock-logistics-barcode
Author: ForgeFlow, Odoo Community Association (OCA)
Author-email: support@odoo-community.org
License: AGPL-3
Platform: UNKNOWN
Classifier: Programming Language :: Python
Classifier: Framework :: Odoo
Classifier: Framework :: Odoo :: 14.0
Classifier: License :: OSI Approved :: GNU Affero General Public License v3
Requires-Python: >=3.6
Requires-Dist: odoo14-addon-product-multi-barcode
Requires-Dist: odoo14-addon-product-supplierinfo-barcode
Requires-Dist: odoo (<14.1dev,>=14.0a)
